zombie/__init__.py
zombie/py.typed
zombie/zombie.py
zombie_py-1.3.dist-info/LICENSE
zombie_py-1.3.dist-info/METADATA
zombie_py-1.3.dist-info/WHEEL
zombie_py-1.3.dist-info/top_level.txt
zombie_py-1.3.dist-info/RECORD
