Metadata-Version: 2.2
Name: zombie-py
Version: 1.3
Summary: Raising Exceptions From the Dead by Re-raising Them With New Exception     Types
Home-page: https://github.com/tybruno/zombie-py
Author: Tyler Bruno
License: MIT
Keywords: python re-raise exceptions
Classifier: License :: OSI Approved :: MIT License
Classifier: Programming Language :: Python :: 3.10
Classifier: Programming Language :: Python :: 3.11
Classifier: Programming Language :: Python :: 3.12
Classifier: Programming Language :: Python :: 3.13
Classifier: Programming Language :: Python :: 3 :: Only
Classifier: Topic :: Software Development :: Libraries :: Python Modules
Requires-Python: >=3.10
License-File: LICENSE
Dynamic: author
Dynamic: classifier
Dynamic: description
Dynamic: description-content-type
Dynamic: home-page
Dynamic: keywords
Dynamic: license
Dynamic: requires-python
Dynamic: summary
